periflow/__init__.py
periflow/auth.py
periflow/cli/__init__.py
periflow/cli/catalog.py
periflow/cli/checkpoint.py
periflow/cli/credential.py
periflow/cli/deployment.py
periflow/cli/gpu.py
periflow/cli/group.py
periflow/cli/key.py
periflow/cli/main.py
periflow/cli/project.py
periflow/client/__init__.py
periflow/client/base.py
periflow/client/catalog.py
periflow/client/checkpoint.py
periflow/client/credential.py
periflow/client/deployment.py
periflow/client/file.py
periflow/client/group.py
periflow/client/project.py
periflow/client/user.py
periflow/cloud/__init__.py
periflow/cloud/storage.py
periflow/configurator/__init__.py
periflow/configurator/base.py
periflow/configurator/credential.py
periflow/configurator/deployment.py
periflow/context.py
periflow/di/__init__.py
periflow/di/injector.py
periflow/di/modules.py
periflow/enums.py
periflow/errors.py
periflow/formatter.py
periflow/logging.py
periflow/modules/__init__.py
periflow/modules/converter/__init__.py
periflow/modules/converter/base.py
periflow/modules/converter/convert.py
periflow/modules/converter/interface.py
periflow/modules/converter/maps.py
periflow/modules/converter/models/blenderbot.py
periflow/modules/converter/models/bloom.py
periflow/modules/converter/models/codegen.py
periflow/modules/converter/models/falcon.py
periflow/modules/converter/models/gpt2.py
periflow/modules/converter/models/gpt_neox.py
periflow/modules/converter/models/gptj.py
periflow/modules/converter/models/llama.py
periflow/modules/converter/models/mistral.py
periflow/modules/converter/models/mpt.py
periflow/modules/converter/models/opt.py
periflow/modules/converter/models/t5.py
periflow/modules/converter/saver.py
periflow/modules/converter/schema.py
periflow/modules/converter/utils.py
periflow/modules/quantizer/__init__.py
periflow/modules/quantizer/awq/__init__.py
periflow/modules/quantizer/awq/base.py
periflow/modules/quantizer/awq/models/gpt_neox.py
periflow/modules/quantizer/awq/models/gptj.py
periflow_client-0.2.2.dist-info/LICENSE
periflow_client-0.2.2.dist-info/METADATA
periflow_client-0.2.2.dist-info/WHEEL
periflow_client-0.2.2.dist-info/entry_points.txt
periflow_client-0.2.2.dist-info/RECORD
